LICENSE
README.md
setup.cfg
setup.py
Geohash_tools.egg-info/PKG-INFO
Geohash_tools.egg-info/SOURCES.txt
Geohash_tools.egg-info/dependency_links.txt
Geohash_tools.egg-info/top_level.txt
geohash_tools/__init__.py
geohash_tools/geohash_tools.py
geohash_tools.egg-info/PKG-INFO
geohash_tools.egg-info/SOURCES.txt
geohash_tools.egg-info/dependency_links.txt
geohash_tools.egg-info/top_level.txt
tests/__init__.py
tests/test_geohash_tools.py